Racial_Block_Voting_tools/Racial_Block_Voting_tools.py
Racial_Block_Voting_tools/__init__.py
Racial_Polarized_Voting_Tools-0.1.0.dist-info/LICENSE.txt
Racial_Polarized_Voting_Tools-0.1.0.dist-info/METADATA
Racial_Polarized_Voting_Tools-0.1.0.dist-info/WHEEL
Racial_Polarized_Voting_Tools-0.1.0.dist-info/top_level.txt
Racial_Polarized_Voting_Tools-0.1.0.dist-info/RECORD
