Metadata-Version: 2.1
Name: Racial-Polarized-Voting-Tools
Version: 0.1.0
Summary: Tool to analyse Racial Polarized Voting
Home-page: https://github.com/RobertEdwardes/Racial_Polarized_Voting_Tools
Author: Robert Edwardes
Author-email: robie@fairlines.org
License: UNKNOWN
Platform: UNKNOWN
Classifier: Development Status :: 4 - Beta
Classifier: License :: OSI Approved :: MIT License
Classifier: Programming Language :: Python :: 3
Classifier: Programming Language :: Python :: 3.6
Classifier: Programming Language :: Python :: 3.7
Classifier: Programming Language :: Python :: 3.8
Classifier: Programming Language :: Python :: 3.9
Classifier: Programming Language :: Python :: 3.10
Classifier: Programming Language :: Python :: 3 :: Only
Requires-Python: >=3.6, <4
License-File: LICENSE.txt
Requires-Dist: pandas
Requires-Dist: matplotlib
Requires-Dist: statsmodels
